roc/punk/__init__.py
roc/punk/commands.py
roc/punk/constants.py
roc/punk/descriptor.json
roc/punk/tasks/__init__.py
roc/punk/tasks/descriptor_report.py
roc/punk/tasks/sbm_query.py
roc/punk/tasks/sbm_report.py
roc/punk/tasks.py
roc/punk/templates/__init__.py
roc/punk/templates/software_report.html
roc/punk/tests/__init__.py
roc/punk/tests/test_punk.py
roc/punk/tests/test_sbm.py
roc_punk-1.1.0.dist-info/LICENSE
roc_punk-1.1.0.dist-info/METADATA
roc_punk-1.1.0.dist-info/WHEEL
roc_punk-1.1.0.dist-info/RECORD
